COPYING
MANIFEST.in
README.rst
_version.py
pyaxo.py
setup.cfg
setup.py
versioneer.py
examples/README.md
examples/axochat.py
examples/axotor.py
examples/create_states.py
examples/name1.py
examples/name2.py
examples/ratchet_watcher.py
examples/smp.py
examples/transfer.py
examples/wh.py
pyaxo.egg-info/PKG-INFO
pyaxo.egg-info/SOURCES.txt
pyaxo.egg-info/dependency_links.txt
pyaxo.egg-info/requires.txt
pyaxo.egg-info/top_level.txt
tests/__init__.py
tests/conftest.py
tests/test_conversations.py
tests/test_db.py
tests/test_states.py
tests/test_utils.py
tests/utils.py
utilities/README.md
utilities/convert_dbs.py
utilities/encrypt_decrypt_file.py
utilities/gen_database_pair.py
utilities/init_conversation.py