Metadata-Version: 1.0
Name: pyaxo
Version: 0.8.2
Summary: Python implementation of the Axolotl ratchet protocol
Home-page: https://github.com/rxcomm/pyaxo
Author: David R. Andersen
Author-email: k0rx@RXcomm.net
License: UNKNOWN
Platform: UNKNOWN
